common.o
custom_ops.cu.o
extensions.o
version.txt
transformer_engine/transformer_engine_paddle.py
transformer_engine/transformer_engine_paddle_pd_.so
transformer_engine_paddle-1.13.0.dist-info/METADATA
transformer_engine_paddle-1.13.0.dist-info/WHEEL
transformer_engine_paddle-1.13.0.dist-info/top_level.txt
transformer_engine_paddle-1.13.0.dist-info/RECORD
