Metadata-Version: 2.1
Name: transformer_engine_paddle
Version: 1.13.0
Summary: Transformer acceleration library - Paddle Paddle Lib
Requires-Dist: paddlepaddle-gpu>=2.6.1
